pyhttpcli/__init__.py
pyhttpcli/__version__.py
pyhttpcli/main.py
pyhttpcli-0.1.0.dist-info/entry_points.txt
pyhttpcli-0.1.0.dist-info/METADATA
pyhttpcli-0.1.0.dist-info/WHEEL
pyhttpcli-0.1.0.dist-info/RECORD
